[
  {
    "id": "1756559834338",
    "timestamp": "2025-08-30T10:17:14.389977-03:00",
    "nome": "",
    "telefone": "",
    "operadora": "Tim",
    "recarga_selecionada": "R$30,00 PAGA R$20,00",
    "senha_app": null,
    "status": "Na fila de espera",
    "admin_comment": ""
  },
  {
    "id": "1756561561934",
    "timestamp": "2025-08-30T10:46:02.064250-03:00",
    "nome": "JEFERSON DA SILVA SANTOS",
    "telefone": "(82) 99915-8412",
    "operadora": "Tim",
    "recarga_selecionada": "R$15,00 PAGA R$10,00",
    "senha_app": "8745",
    "status": "Na fila de espera",
    "admin_comment": ""
  },
  {
    "id": "1756640740612",
    "timestamp": "2025-08-31T08:45:40.730762-03:00",
    "nome": "Jeferson",
    "telefone": "(82) 99915-8412",
    "operadora": "Tim",
    "recarga_selecionada": "R$20,00 PAGA R$15,00",
    "senha_app": "4785",
    "status": "Processando",
    "admin_comment": ""
  },
  {
    "id": "1756642748587",
    "timestamp": "2025-08-31T09:19:08.612105-03:00",
    "nome": "JEFERSON DA SILVA SANTOS",
    "telefone": "(82) 99915-8412",
    "operadora": "Tim",
    "recarga_selecionada": "R$20,00 PAGA R$15,00",
    "senha_app": "1545",
    "status": "Concluída",
    "admin_comment": ""
  }
]